{
    "ZREMRANGEBYRANK": {
        "summary": "Remove all members in a sorted set within the given indexes",
        "complexity": "O(log(N)+M) with N being the number of elements in the sorted set and M the number of elements removed by the operation.",
        "group": "sorted_set",
        "since": "2.0.0",
        "arity": 4,
        "function": "zremrangebyrankCommand",
        "command_flags": [
            "WRITE"
        ],
        "acl_categories": [
            "SORTEDSET"
        ],
        "key_specs": [
            {
                "flags": [
                    "RW",
                    "DELETE"
                ],
                "begin_search": {
                    "index": {
                        "pos": 1
                    }
                },
                "find_keys": {
                    "range": {
                        "lastkey": 0,
                        "step": 1,
                        "limit": 0
                    }
                }
            }
        ],
        "arguments": [
            {
                "name": "key",
                "type": "key",
                "key_spec_index": 0
            },
            {
                "name": "start",
                "type": "integer"
            },
            {
                "name": "stop",
                "type": "integer"
            }
        ]
    }
}
